autolibs/__init__.py
autolibs-0.2.0.dist-info/licenses/LICENSE
autolibs-0.2.0.dist-info/METADATA
autolibs-0.2.0.dist-info/WHEEL
autolibs-0.2.0.dist-info/top_level.txt
autolibs-0.2.0.dist-info/RECORD
