Metadata-Version: 2.4
Name: autolibs
Version: 0.2.0
Summary: Auto-import Python Libraries
Home-page: https://github.com/hsnaidu/autolibs
Author: HARI_PRASAD_S
Author-email: hariprasad2k06@gmail.com
License: MIT
Classifier: Programming Language :: Python :: 3
Classifier: Operating System :: OS Independent
Requires-Python: >=3.7
License-File: LICENSE
Requires-Dist: numpy
Requires-Dist: pandas
Requires-Dist: matplotlib
Requires-Dist: seaborn
Dynamic: author
Dynamic: author-email
Dynamic: classifier
Dynamic: description
Dynamic: description-content-type
Dynamic: home-page
Dynamic: license
Dynamic: license-file
Dynamic: requires-dist
Dynamic: requires-python
Dynamic: summary
